sinistra/__init__.py
sinistra/astropy_helpers.py
sinistra/classes.py
sinistra/phot.py
sinistra/utilities.py
sinistra-0.3.3.dist-info/DESCRIPTION.rst
sinistra-0.3.3.dist-info/METADATA
sinistra-0.3.3.dist-info/RECORD
sinistra-0.3.3.dist-info/WHEEL
sinistra-0.3.3.dist-info/metadata.json
sinistra-0.3.3.dist-info/top_level.txt
