Metadata-Version: 2.0
Name: sinistra
Version: 0.3.3
Summary: A collection of astronomy related tools.
Home-page: http://sinistra.readthedocs.io/en/latest/
Author: Gillen Brown
Author-email: gillenbrown@gmail.com
License: MIT
Keywords: astronomy tools utilities astrophysics
Platform: UNKNOWN
Requires-Dist: astropy
Requires-Dist: numpy
Requires-Dist: scipy
